spyrite/__init__.py
spyrite/__main__.py
spyrite/make_sprite.py
spyrite-0.2.0.dist-info/WHEEL
spyrite-0.2.0.dist-info/entry_points.txt
spyrite-0.2.0.dist-info/METADATA
spyrite-0.2.0.dist-info/RECORD
