Metadata-Version: 2.3
Name: spyrite
Version: 0.2.0
Summary: Add your description here
Requires-Dist: pillow>=12.0.0
Requires-Python: >=3.12
